CursesMenu/CursesMenu.py
CursesMenu/__init__.py
CursesMenu-0.0.1a0.dist-info/LICENSE
CursesMenu-0.0.1a0.dist-info/METADATA
CursesMenu-0.0.1a0.dist-info/WHEEL
CursesMenu-0.0.1a0.dist-info/top_level.txt
CursesMenu-0.0.1a0.dist-info/RECORD
