Metadata-Version: 2.1
Name: CursesMenu
Version: 0.0.1a0
Summary: A GTK inspired widget engine using curses for use with command line interfaces.
Home-page: https://github.com/scoutchorton/CursesMenu
Author: scoutchorton
Author-email: scoutchorton@gmail.com
License: UNKNOWN
Platform: UNKNOWN
Classifier: Programming Language :: Python :: 3
Classifier: License :: OSI Approved :: GNU General Public License v3 (GPLv3)
Classifier: Operating System :: OS Independent
Classifier: Development Status :: 3 - Alpha
Classifier: Environment :: Console :: Curses
Requires-Python: >=3.6
